mediqbox/__init__.py
mediqbox/abc.py
mediqbox/download.py
mediqbox/pubmed.py
mediqbox/sendmail.py
mediqbox-0.1.0.dist-info/LICENSE
mediqbox-0.1.0.dist-info/METADATA
mediqbox-0.1.0.dist-info/WHEEL
mediqbox-0.1.0.dist-info/top_level.txt
mediqbox-0.1.0.dist-info/RECORD
